workstreams/__init__.py
workstreams/__version__.py
workstreams/client.py
workstreams/exceptions.py
workstreams/utils.py
workstreams/resources/__init__.py
workstreams/resources/base.py
workstreams/resources/goals.py
workstreams/resources/labels.py
workstreams/resources/tasks.py
workstreams-1.0.6.dist-info/LICENSE
workstreams-1.0.6.dist-info/METADATA
workstreams-1.0.6.dist-info/WHEEL
workstreams-1.0.6.dist-info/top_level.txt
workstreams-1.0.6.dist-info/RECORD
