Metadata-Version: 2.1
Name: workstreams
Version: 1.0.6
Summary: A Python client library for Workstreams.ai
Home-page: https://github.com/ProdPerfect/workstreams
Author: Lemuel Boyce
Author-email: lemuel@prodperfect.com
License: MIT
Platform: UNKNOWN
Classifier: Programming Language :: Python :: 3
Classifier: Programming Language :: Python :: 3.6
Classifier: Programming Language :: Python :: 3.7
Classifier: Operating System :: OS Independent
Requires-Python: >=3.6
Requires-Dist: requests (>=2.19.0)
